CHANGELOG.rst
COPYING
MANIFEST.in
README.rst
setup.cfg
setup.py
./shallowlearn/word2vec_inner.pyx
ShallowLearn.egg-info/PKG-INFO
ShallowLearn.egg-info/SOURCES.txt
ShallowLearn.egg-info/dependency_links.txt
ShallowLearn.egg-info/requires.txt
ShallowLearn.egg-info/top_level.txt
scripts/document_classification_20newsgroups.py
scripts/plot_out_of_core_classification.py
shallowlearn/__init__.py
shallowlearn/models.py
shallowlearn/utils.py
shallowlearn/voidptr.h
shallowlearn/word2vec.py
shallowlearn/word2vec_inner.c
shallowlearn/word2vec_inner.pxd
shallowlearn/word2vec_inner.pyx