Metadata-Version: 1.1
Name: ShallowLearn
Version: 0.0.5
Summary: A collection of supervised learning models based on shallow neural network approaches (e.g., word2vec and fastText) with some additional exclusive features
Home-page: https://github.com/giacbrd/ShallowLearn
Author: Giacomo Berardi
Author-email: barnets@gmail.com
License: UNKNOWN
Platform: UNKNOWN
Classifier: Programming Language :: Python :: 2.7
Classifier: Programming Language :: Python :: 3.5
Classifier: Environment :: Console
Classifier: Intended Audience :: Science/Research
Classifier: License :: OSI Approved :: GNU Lesser General Public License v3 or later (LGPLv3+)
Classifier: Operating System :: OS Independent
Classifier: Topic :: Scientific/Engineering :: Artificial Intelligence
Classifier: Topic :: Scientific/Engineering :: Information Analysis
Classifier: Topic :: Text Processing :: Linguistic
